{
  "version": 1,
  "contract_id": "ui_polish_slice2_color_mode_authority",
  "feature_id": "ui_polish_color_mode_authority",
  "workflow_type": "viewer_first",
  "plan_path": "docs/notes/ui_polish_slice2_color_mode_authority_PHASED_PLAN.md",
  "allowed_mutation_scope": [
    "docs/contracts",
    "docs/notes/ui_polish_sprint_overview_PHASED_PLAN.md",
    "docs/notes/ui_polish_slice2_color_mode_authority_PHASED_PLAN.md",
    "ui/fractal_binding_surface_v1.ui_schema.json",
    "ui_app/src/fractal_types.h",
    "ui_app/src/escape_time_coloring.h",
    "ui_app/src/fractal_renderer.cu",
    "ui_app/src/schema_binding.h",
    "ui_app/src/schema_binding.cpp",
    "ui_app/tests/test_ui_schema.cpp",
    "ui_app/tests/test_schema_binding.cpp",
    "ui_app/tests/test_fractal_sample_pipeline.cpp",
    "ui_app/tests/test_fractal_family_rules.cpp"
  ],
  "required_operator_inputs": [
    "color mode schema/runtime owner files",
    "focused color-mode tests",
    "published runtime"
  ],
  "forbidden_operator_prompts": [
    "chat-only color redesign",
    "unbounded programmable color spike",
    "silent coloring fallback"
  ],
  "required_defaults": {
    "schema_authority": "single_source",
    "color_authority": "single_public_mode_surface",
    "slice_scope": "color_mode_authority_only"
  },
  "forbidden_defaults": {
    "main_cpp_one_off_color_override": "forbidden",
    "second_color_source_of_truth": "forbidden",
    "off_topic_resolution_policy_change": "forbidden"
  },
  "required_validation_commands": [
    "py -3.14 tools/viewer_host_validate_slice_contract.py --contract docs/contracts/ui_polish_slice2_color_mode_authority.contract.json --out-json artifacts/validation/ui_polish_slice2_color_mode_authority_contract.json",
    "py -3.14 tools/viewer_host_assert_phased_plan_sync.py"
  ],
  "required_acceptance_assertions": [
    {
      "assertion_id": "slice2_contract_schema_valid",
      "description": "Slice 2 color-authority contract validates with structured assertions enabled",
      "evidence_kind": "validator_json",
      "artifact_path": "artifacts/validation/ui_polish_slice2_color_mode_authority_contract.json",
      "json_path": "checks.contract_schema_valid",
      "equals": true
    },
    {
      "assertion_id": "slice2_plan_sync_ok",
      "description": "Slice 2 phased plan stays synchronized while the color-authority slice is active",
      "evidence_kind": "validator_json",
      "artifact_path": "artifacts/validation/viewer_host_assert_phased_plan_sync.json",
      "json_path": "ok",
      "equals": true
    }
  ]
}